{"nw377": [], "nw378": [], "nw379": [], "nw380": [], "nw382": [], "nw383": [], "nw384": [], "nw385": [], "nw386": [], "nw387": [], "nw388": [], "nw389": [], "nw390": [], "nw391": [], "nw392": [], "nw393": [], "nw394": [], "nw395": [], "nw396": [], "nw397": [], "nw398": [], "nw399": [], "nw400": [], "nw401": [], "nw402": [], "nw403": [], "nw404": [], "nw405": [], "nw406": [], "nw407": [], "nw408": [], "nw410": [], "nw411": [], "nw412": [], "nw413": [], "nw414": [], "nw415": [], "nw417": [], "nw418": [], "nw421": [], "nw422": [], "nw424": [], "nw425": [], "nw426": [], "nw427": [], "nw428": [], "nw429": [], "nw430": [], "nw432": [], "nw434": [], "nw435": [], "nw436": [], "nw437": [], "nw440": [], "nw442": [], "nw443": [], "nw444": [], "nw445": [], "nw446": [], "nw447": [], "nw448": [], "nw450": [], "nw451": [], "nw452": [], "nw453": [], "nw454": [], "nw455": [], "nw456": [], "nw457": [], "nw458": [], "nw459": [], "nw461": [], "nw462": [], "nw463": [], "nw464": [], "nw465": [], "nw466": [], "nw467": [], "nw468": [], "nw469": [], "nw470": [], "nw471": [], "nw472": [], "nw474": [], "nw476": [], "nw478": [], "nw480": [], "nw482": [], "nw483": [], "nw484": [], "nw485": [], "nw486": [], "nw487": [], "nw488": [], "nw490": [], "nw491": [], "nw493": [], "nw494": [], "nw495": [], "nw496": [], "nw497": [], "nw498": [], "nw499": [], "nw500": [], "nw501": [], "nw502": [], "nw503": [], "nw504": [], "nw505": [], "nw506": [], "nw507": [], "nw508": [], "nw510": [], "nw511": [], "nw516": [], "nw517": [], "nw518": [], "nw520": [], "nw521": [], "nw522": [], "nw523": [], "nw524": [], "nw525": [], "nw526": [], "nw527": [], "nw528": []}